pineaoth/__init__.py
pineaoth/main.py
pineaoth/mainpreveruis.py
pineaoth/cli/__init__.py
pineaoth/cli/commands.py
pineaoth/core/__init__.py
pineaoth/core/manager.py
pineaoth/core/otp.py
pineaoth/core/utils.py
pineaoth/database/__init__.py
pineaoth/database/db.py
pineaoth-1.0.1.dist-info/licenses/LICENSE
pineaoth-1.0.1.dist-info/METADATA
pineaoth-1.0.1.dist-info/WHEEL
pineaoth-1.0.1.dist-info/entry_points.txt
pineaoth-1.0.1.dist-info/top_level.txt
pineaoth-1.0.1.dist-info/RECORD
